<annotation>
	<folder>2</folder>
	<filename>img00459.jpg</filename>
	<path>D:\x\照片\Annotation\2\img00459.jpg</path>
	<source>
		<database>Unknown</database>
	</source>
	<size>
		<width>256</width>
		<height>256</height>
		<depth>3</depth>
	</size>
	<segmented>0</segmented>
	<object>
		<name>no_mask</name>
		<pose>Unspecified</pose>
		<truncated>0</truncated>
		<difficult>0</difficult>
		<bndbox>
			<xmin>51</xmin>
			<ymin>39</ymin>
			<xmax>85</xmax>
			<ymax>72</ymax>
		</bndbox>
	</object>
	<object>
		<name>mask</name>
		<pose>Unspecified</pose>
		<truncated>0</truncated>
		<difficult>0</difficult>
		<bndbox>
			<xmin>130</xmin>
			<ymin>33</ymin>
			<xmax>171</xmax>
			<ymax>73</ymax>
		</bndbox>
	</object>
</annotation>
