<annotation>
	<folder>2</folder>
	<filename>img01285.jpg</filename>
	<path>D:\x\照片\Annotation\2\img01285.jpg</path>
	<source>
		<database>Unknown</database>
	</source>
	<size>
		<width>256</width>
		<height>256</height>
		<depth>3</depth>
	</size>
	<segmented>0</segmented>
	<object>
		<name>mask</name>
		<pose>Unspecified</pose>
		<truncated>0</truncated>
		<difficult>0</difficult>
		<bndbox>
			<xmin>113</xmin>
			<ymin>85</ymin>
			<xmax>155</xmax>
			<ymax>119</ymax>
		</bndbox>
	</object>
</annotation>
