<annotation>
	<folder>3</folder>
	<filename>img02375.jpg</filename>
	<path>E:\3\img02375.jpg</path>
	<source>
		<database>Unknown</database>
	</source>
	<size>
		<width>256</width>
		<height>256</height>
		<depth>3</depth>
	</size>
	<segmented>0</segmented>
	<object>
		<name>mask</name>
		<pose>Unspecified</pose>
		<truncated>0</truncated>
		<difficult>0</difficult>
		<bndbox>
			<xmin>87</xmin>
			<ymin>22</ymin>
			<xmax>126</xmax>
			<ymax>72</ymax>
		</bndbox>
	</object>
	<object>
		<name>no_mask</name>
		<pose>Unspecified</pose>
		<truncated>0</truncated>
		<difficult>0</difficult>
		<bndbox>
			<xmin>183</xmin>
			<ymin>32</ymin>
			<xmax>229</xmax>
			<ymax>78</ymax>
		</bndbox>
	</object>
</annotation>
