<annotation>
	<folder>2</folder>
	<filename>img00922.jpg</filename>
	<path>D:\x\照片\Annotation\2\img00922.jpg</path>
	<source>
		<database>Unknown</database>
	</source>
	<size>
		<width>256</width>
		<height>256</height>
		<depth>3</depth>
	</size>
	<segmented>0</segmented>
	<object>
		<name>mask</name>
		<pose>Unspecified</pose>
		<truncated>0</truncated>
		<difficult>0</difficult>
		<bndbox>
			<xmin>67</xmin>
			<ymin>60</ymin>
			<xmax>148</xmax>
			<ymax>129</ymax>
		</bndbox>
	</object>
</annotation>
